profanity_filter/__init__.py
profanity_filter/config.py
profanity_filter/console.py
profanity_filter/profanity_filter.py
profanity_filter/spacy_component.py
profanity_filter/spacy_utlis.py
profanity_filter/types_.py
profanity_filter/web.py
profanity_filter/analysis/__init__.py
profanity_filter/analysis/deep.py
profanity_filter/analysis/morphological.py
profanity_filter/analysis/multilingual.py
profanity_filter/data/en.aff
profanity_filter/data/en.dic
profanity_filter/data/en_core_web_sm_profane_words.txt
profanity_filter/data/ru.aff
profanity_filter/data/ru.dic
profanity_filter/data/ru_core_news_sm_profane_words.txt
profanity_filter2-1.4.3.dist-info/LICENSE
profanity_filter2-1.4.3.dist-info/METADATA
profanity_filter2-1.4.3.dist-info/WHEEL
profanity_filter2-1.4.3.dist-info/entry_points.txt
profanity_filter2-1.4.3.dist-info/top_level.txt
profanity_filter2-1.4.3.dist-info/RECORD
