Metadata-Version: 2.1
Name: profanity-filter2
Version: 1.4.3
Summary: A Python library for detecting and filtering profanity
Home-page: https://github.com/neorusa/profanity-filter
Author: Roman Inflianskas
Author-email: infroma@gmail.com
Maintainer: Ruslan Gareev
Maintainer-email: mail@ruslangareev.ru
License: https://www.gnu.org/licenses/gpl-3.0.en.html
Platform: UNKNOWN
Requires-Python: >=3.7,<4.0
License-File: LICENSE
Requires-Dist: cached-property (<2.0,>=1.5)
Requires-Dist: more-itertools (<9.0,>=8.0)
Requires-Dist: ordered-set-stubs (<0.2.0,>=0.1.3)
Requires-Dist: ordered-set (<4.0,>=3.0)
Requires-Dist: poetry-version (<0.2.0,>=0.1.3)
Requires-Dist: pydantic (<2.0,>=1.3)
Requires-Dist: redis (<4.0,>=3.2)
Requires-Dist: ruamel.yaml (<0.16.0,>=0.15.89)
Requires-Dist: spacy (<4.0,>=3.0)
Requires-Dist: dataclasses (<0.7.0,>=0.6.0) ; python_version >= "3.7" and python_version < "3.9"
Provides-Extra: deep-analysis
Requires-Dist: hunspell (<0.6.0,>=0.5.5) ; extra == 'deep-analysis'
Requires-Dist: python-Levenshtein (<0.13.0,>=0.12.0) ; extra == 'deep-analysis'
Requires-Dist: regex (<2022.0.0,>=2020.0.20) ; extra == 'deep-analysis'
Provides-Extra: multilingual
Requires-Dist: polyglot (<17.0,>=16.7) ; extra == 'multilingual'
Requires-Dist: pycld2 (==0.31) ; extra == 'multilingual'
Requires-Dist: PyICU (<3.0,>=2.4) ; extra == 'multilingual'
Provides-Extra: pymorphy2-ru
Requires-Dist: pymorphy2-dicts-ru (<3.0.0,>=2.4.404381) ; extra == 'pymorphy2-ru'
Provides-Extra: pymorphy2-uk
Requires-Dist: pymorphy2-dicts-uk (<3.0.0,>=2.4.1) ; extra == 'pymorphy2-uk'
Provides-Extra: web
Requires-Dist: appdirs (<2.0.0,>=1.4.3) ; extra == 'web'
Requires-Dist: fastapi (<0.46.0,>=0.45.0) ; extra == 'web'
Requires-Dist: uvicorn (<0.12.0,>=0.11.1) ; extra == 'web'
